redox/__init__.py
redox-0.1.0.dist-info/WHEEL
redox-0.1.0.dist-info/METADATA
redox-0.1.0.dist-info/RECORD
