Metadata-Version: 2.1
Name: redox
Version: 0.1.0
Summary: A stream processing library for redis streams
Author: Sascha Desch
Author-email: sascha.desch@hotmail.com
Requires-Python: >=3.9,<4.0
Classifier: Programming Language :: Python :: 3
Classifier: Programming Language :: Python :: 3.10
Classifier: Programming Language :: Python :: 3.9
